[{"Name":"Абрикосовый","HexValue":"#FBCEB1"},{"Name":"Крайоловый Абрикос","HexValue":"#FDD5B1"},{"Name":"Абрикосовый Крайола","HexValue":"#FDD9B5"},{"Name":"Тёмно-персиковый","HexValue":"#FFDAB9"},{"Name":"Желтовато-белый","HexValue":"#FFE2B7"},{"Name":"Мокасиновый","HexValue":"#FFE4B5"},{"Name":"Персиковый","HexValue":"#FFE5B4"},{"Name":"Жёлто-розовый","HexValue":"#FFE4B2"},{"Name":"Банана мания","HexValue":"#FAE7B5"},{"Name":"Пшеничный","HexValue":"#F5DEB3"},{"Name":"Жёлто-персиковый","HexValue":"#FADFAD"},{"Name":"Белый навахо","HexValue":"#FFDEAD"},{"Name":"Светло-песочный","HexValue":"#FDEAA8"},{"Name":"Бледно-золотистый","HexValue":"#EEE8AA"},{"Name":"Цвет пергидрольной блондинки","HexValue":"#EEE6A3"},{"Name":"Зелёно-жёлтый Крайола","HexValue":"#F0E891"},{"Name":"Светлый хаки","HexValue":"#F0E68C"},{"Name":"Кожа буйвола (палевый)","HexValue":"#F0DC82"},{"Name":"Старый лён","HexValue":"#EEDC82"},{"Name":"Светлая слоновая кость","HexValue":"#E6D690"},{"Name":"Бледный желтовато-зелёный","HexValue":"#F0D698"},{"Name":"Маисовый","HexValue":"#EDD19C"},{"Name":"Золотой Крайола","HexValue":"#E7C697"},{"Name":"Циннвальдит","HexValue":"#EBC2AF"},{"Name":"Песок пустыни","HexValue":"#EFCDB8"},{"Name":"Циннвальдитово-розовый","HexValue":"#FFCBBB"},{"Name":"Бледный пурпурно-розовый","HexValue":"#FDBDBA"},{"Name":"Дыня Крайола","HexValue":"#FDBCB4"},{"Name":"Светло-коралловый","HexValue":"#FFBCAD"},{"Name":"Бледный желтовато-розовый","HexValue":"#FFC8A8"},{"Name":"Персиковый Крайола","HexValue":"#FFCFAB"},{"Name":"Оранжево-персиковый","HexValue":"#FFCC99"},{"Name":"Бледный оранжево-жёлтый","HexValue":"#FFCA86"},{"Name":"Макароны и сыр","HexValue":"#FFBD88"},{"Name":"Светлый желтовато-розовый","HexValue":"#FFB28B"},{"Name":"Сомон","HexValue":"#EFAF8C"},{"Name":"Перекатиполе","HexValue":"#DEAA88"},{"Name":"Цвет загара (Жёлто-коричневый)","HexValue":"#D2B48C"},{"Name":"Экрю","HexValue":"#CDB891"},{"Name":"Хаки","HexValue":"#C3B091"},{"Name":"Светлый серый","HexValue":"#C2A894"},{"Name":"Розовато-серый","HexValue":"#C8A696"},{"Name":"Светлый пурпурно-серый","HexValue":"#C8A99E"},{"Name":"Светлый синевато-серый","HexValue":"#BEADA1"},{"Name":"Светлый зеленовато-белый","HexValue":"#BAAF96"},{"Name":"Галечный серый","HexValue":"#B8B799"},{"Name":"Болотный","HexValue":"#ACB78E"},{"Name":"Зелёно-бежевый","HexValue":"#BEBD7F"},{"Name":"Оливково-зелёный Крайола","HexValue":"#BAB86C"},{"Name":"Тёмный хаки","HexValue":"#BDB76B"},{"Name":"Песочно-жёлтый","HexValue":"#C6A664"},{"Name":"Серовато-зеленовато-жёлтый","HexValue":"#C4A55F"},{"Name":"Серовато-жёлтый","HexValue":"#CEA262"},{"Name":"Коричнево-жёлтый цвета увядших листьев","HexValue":"#C19A6B"},{"Name":"Античная латунь","HexValue":"#CD9575"},{"Name":"Коричневато-розовый","HexValue":"#CD9A7B"},{"Name":"Серовато-желтовато-розовый","HexValue":"#D39B85"},{"Name":"Серовато-розовый","HexValue":"#CF9B8F"},{"Name":"Серовато-пурпурно-розовый","HexValue":"#CC9293"},{"Name":"Пюсовый","HexValue":"#CC8899"},{"Name":"Розово-коричневый","HexValue":"#BC8F8F"},{"Name":"Бледно-пурпурный","HexValue":"#AE848B"},{"Name":"Пастельно-фиолетовый","HexValue":"#A18594"},{"Name":"Розовый Маунтбэттена","HexValue":"#997A8D"},{"Name":"Бледно-фиолетовый","HexValue":"#957B8D"},{"Name":"Бледный пурпурно-синий","HexValue":"#8A7F8E"},{"Name":"Тёмный Телегрей","HexValue":"#82898F"},{"Name":"Серая белка","HexValue":"#78858B"},{"Name":"Серый шифер, аспидно-серый","HexValue":"#708090"},{"Name":"Светлый аспидно-серый","HexValue":"#778899"},{"Name":"Светлый пурпурно-синий","HexValue":"#837DA2"},{"Name":"Перламутрово-фиолетовый","HexValue":"#8673A1"},{"Name":"Светло-фиолетовый","HexValue":"#876C99"},{"Name":"Блестящий фиолетовый","HexValue":"#755D9A"},{"Name":"Королевский пурпурный Крайола","HexValue":"#7851A9"},{"Name":"Яркий фиолетовый Крайола","HexValue":"#8F509D"},{"Name":"Сливовый Крайола","HexValue":"#8E4585"},{"Name":"Сигнальный фиолетовый","HexValue":"#924E7D"},{"Name":"Розовато-лилово-серый","HexValue":"#915F6D"},{"Name":"Медно-розовый (Бледный розовато-лиловый)","HexValue":"#996666"},{"Name":"Тёмно-каштановый","HexValue":"#986960"},{"Name":"Светлый серовато-красновато-коричневый","HexValue":"#966A57"},{"Name":"Светлый серовато-коричневый","HexValue":"#946B54"},{"Name":"Светло-коричневый","HexValue":"#987654"},{"Name":"Тёмный жёлто-коричневый","HexValue":"#918151"},{"Name":"Серовато-желтовато-зелёный","HexValue":"#90845B"},{"Name":"Полумрак Крайола","HexValue":"#8A795D"},{"Name":"Светлый оливково-серый","HexValue":"#887359"},{"Name":"Светлый коричневато-серый","HexValue":"#8B6D5C"},{"Name":"Красновато-серый","HexValue":"#8B6C62"},{"Name":"Пурпурно-серый","HexValue":"#88706B"},{"Name":"Средний серый","HexValue":"#817066"},{"Name":"Синевато-серый","HexValue":"#7D746D"},{"Name":"Зеленовато-серый","HexValue":"#7A7666"},{"Name":"Хаки, защитный, камуфляжный","HexValue":"#78866B"},{"Name":"Цементно-серый (цементный)","HexValue":"#7D8471"},{"Name":"Пыльно-серый","HexValue":"#7D7F7D"},{"Name":"Серый","HexValue":"#808080"},{"Name":"Перламутровый тёмно-серый","HexValue":"#828282"},{"Name":"Перламутровый мышино-серый","HexValue":"#898176"},{"Name":"Каменно-серый","HexValue":"#8B8C7A"},{"Name":"Бледно-зелёно-серый","HexValue":"#8D917A"},{"Name":"Лягушки в обмороке","HexValue":"#7B917B"},{"Name":"Транспортный серый","HexValue":"#8D948D"},{"Name":"Телегрей","HexValue":"#909090"},{"Name":"Бледный синий","HexValue":"#919192"},{"Name":"Серый Крайола","HexValue":"#95918C"},{"Name":"Кварцевый","HexValue":"#99958C"},{"Name":"Сигнальный серый","HexValue":"#969992"},{"Name":"Перламутровый светло-серый","HexValue":"#9C9C9C"},{"Name":"Серый нейтральный","HexValue":"#A0A0A4"},{"Name":"Серое окно","HexValue":"#9DA1AA"},{"Name":"Ламантин","HexValue":"#979AAA"},{"Name":"Бело-алюминиевый","HexValue":"#A5A5A5"},{"Name":"Розовый кварц","HexValue":"#AA98A9"},{"Name":"Оперный розовато-лиловый","HexValue":"#B784A7"},{"Name":"Светло-пурпурный","HexValue":"#BA7FA2"},{"Name":"Светлый красновато-пурпурный","HexValue":"#BB6C8A"},{"Name":"Турецкий розовый","HexValue":"#B57281"},{"Name":"Розово-золотой","HexValue":"#B76E79"},{"Name":"Светлый серовато-пурпурно-красный","HexValue":"#B27070"},{"Name":"Светло-серовато-красный","HexValue":"#B17267"},{"Name":"Светлый серовато-желтовато-коричневый","HexValue":"#B48764"},{"Name":"Бежево-красный","HexValue":"#C1876B"},{"Name":"Старинный розовый","HexValue":"#C08081"},{"Name":"Бледный красновато-пурпурный","HexValue":"#AC7580"},{"Name":"Бобровый","HexValue":"#9F8170"},{"Name":"Жёлто-серый","HexValue":"#8F8B66"},{"Name":"Серо-бежевый","HexValue":"#9E9764"},{"Name":"Оливково-жёлтый","HexValue":"#999950"},{"Name":"Охра жёлтая","HexValue":"#AEA04B"},{"Name":"Латунный","HexValue":"#B5A642"},{"Name":"Умеренный зеленовато-жёлтый","HexValue":"#C4A43D"},{"Name":"Жёлто-золотой","HexValue":"#CDA434"},{"Name":"Умеренный жёлтый","HexValue":"#D79D41"},{"Name":"Старое золото","HexValue":"#CFB53B"},{"Name":"Лимонно-жёлтый","HexValue":"#C7B446"},{"Name":"Блестящий жёлто-зелёный","HexValue":"#CED23A"},{"Name":"Грушево-зелёный","HexValue":"#D1E231"},{"Name":"Грушевый","HexValue":"#EFD334"},{"Name":"Шафраново-жёлтый","HexValue":"#F5D033"},{"Name":"Шафрановый","HexValue":"#F4C430"},{"Name":"Блестящий жёлтый","HexValue":"#FFCF40"},{"Name":"Восход солнца","HexValue":"#FFCF48"},{"Name":"Горчичный","HexValue":"#FFDB58"},{"Name":"Светлый зеленовато-жёлтый","HexValue":"#FFDE5A"},{"Name":"Светлый глубокий жёлтый","HexValue":"#FFD35F"},{"Name":"Оранжево-жёлтый Крайола","HexValue":"#F8D568"},{"Name":"Одуванчиковый","HexValue":"#FDDB6D"},{"Name":"Золотарник Крайола","HexValue":"#FCD975"},{"Name":"Песочный","HexValue":"#FCDD76"},{"Name":"Бледный зеленовато-жёлтый","HexValue":"#FFDF84"},{"Name":"Бледно-жёлтый","HexValue":"#FFDB8B"},{"Name":"Жёлтый Крайола","HexValue":"#FCE883"},{"Name":"Светло-золотистый","HexValue":"#FFEC8B"},{"Name":"Канареечный (ярко-жёлтый)","HexValue":"#FFFF99"},{"Name":"Бледный весенний бутон","HexValue":"#ECEBBD"},{"Name":"Весенне-зелёный Крайола","HexValue":"#ECEABE"},{"Name":"Сливочный","HexValue":"#F2E8C9"},{"Name":"Зеленовато-белый","HexValue":"#F5E6CB"},{"Name":"Синевато-белый","HexValue":"#F9DFCF"},{"Name":"Пурпурно-белый","HexValue":"#FADBC8"},{"Name":"Бисквитный","HexValue":"#FFE4C4"},{"Name":"Очищенный миндаль","HexValue":"#FFEBCD"},{"Name":"Побег папайи","HexValue":"#FFEFD5"},{"Name":"Белый-антик","HexValue":"#FAEBD7"},{"Name":"Бедра испуганной нимфы","HexValue":"#FAEEDD"},{"Name":"Бежевый","HexValue":"#F5F5DC"},{"Name":"Цвет шелковистых нитевидных пестиков початков неспелой кукурузы","HexValue":"#FFF8DC"},{"Name":"Цвет слоновой кости","HexValue":"#FFFDDF"},{"Name":"Светло-жёлтый","HexValue":"#FFFFE0"},{"Name":"Космические сливки","HexValue":"#FFF8E7"},{"Name":"Старое кружево","HexValue":"#FDF5E6"},{"Name":"Кремовый","HexValue":"#FDF4E3"},{"Name":"Льняной","HexValue":"#FAF0E6"},{"Name":"Цвет морской раковины (Морская пена)","HexValue":"#FFF5EE"},{"Name":"Цветочный белый","HexValue":"#FFFAF0"},{"Name":"Слоновая кость","HexValue":"#FFFFF0"},{"Name":"Белоснежный","HexValue":"#FFFAFA"},{"Name":"Белый","HexValue":"#FFFFFF"},{"Name":"Призрачно-белый","HexValue":"#F8F8FF"},{"Name":"Магнолия","HexValue":"#F8F4FF"},{"Name":"Синяя Элис","HexValue":"#F0F8FF"},{"Name":"Небесная лазурь","HexValue":"#F0FFFF"},{"Name":"Мятно-кремовый","HexValue":"#F5FFFA"},{"Name":"Дымчато-белый","HexValue":"#F5F5F5"},{"Name":"Розовато-лавандовый","HexValue":"#FFF0F5"},{"Name":"Медовый","HexValue":"#F0FFF0"},{"Name":"Светлый циан","HexValue":"#E0FFFF"},{"Name":"Лавандовый (Лаванда)","HexValue":"#E6E6FA"},{"Name":"Светло-розовато-лиловый","HexValue":"#DCD0FF"},{"Name":"Барвинковый (Барвинок, перванш)","HexValue":"#CCCCFF"},{"Name":"Барвинок Крайола","HexValue":"#C5D0E6"},{"Name":"Бороды Абдель-Керима","HexValue":"#D5D5D5"},{"Name":"Светло-серый","HexValue":"#D7D7D7"},{"Name":"Лесной волк","HexValue":"#DBD7D2"},{"Name":"Гейнсборо","HexValue":"#DCDCDC"},{"Name":"Светлый Телегрей","HexValue":"#D0D0D0"},{"Name":"Гридеперлевый","HexValue":"#C7D0CC"},{"Name":"Очень бледный синий","HexValue":"#C1CACA"},{"Name":"Серебристый (Серебряный)","HexValue":"#C0C0C0"},{"Name":"Светло-серебристый","HexValue":"#C9C0BB"},{"Name":"Серебряный Крайола","HexValue":"#CDC5C2"},{"Name":"Очень бледный пурпурно-синий","HexValue":"#CBBAC5"},{"Name":"Очень бледный фиолетовый","HexValue":"#D8B1BF"},{"Name":"Очень светло-пурпурный","HexValue":"#E3A9BE"},{"Name":"Бледно-каштановый","HexValue":"#DDADAF"},{"Name":"Бледно-песочный","HexValue":"#DABDAB"},{"Name":"Серый шёлк","HexValue":"#CAC4B0"},{"Name":"Серый зелёный чай","HexValue":"#CADABA"},{"Name":"Умеренно зелёный","HexValue":"#C0DCC0"},{"Name":"Бело-зелёный","HexValue":"#BDECB6"},{"Name":"Тёмный зелёный чай","HexValue":"#BADBAD"},{"Name":"Зелёный лишайник, мох (Цвет зелёного мха)","HexValue":"#ADDFAD"},{"Name":"Серо-зелёный","HexValue":"#ACE1AF"},{"Name":"Бабушкины яблоки","HexValue":"#A8E4A0"},{"Name":"Очень светлый синевато-зелёный","HexValue":"#A0D6B4"},{"Name":"Морской зелёный Крайола","HexValue":"#9FE2BF"},{"Name":"Магическая мята","HexValue":"#AAF0D1"},{"Name":"Пыльный голубой","HexValue":"#B0E0E6"},{"Name":"Светлосиний","HexValue":"#ADD8E6"},{"Name":"Бледно-васильковый","HexValue":"#ABCDEF"},{"Name":"Светло-синий","HexValue":"#A6CAF0"},{"Name":"Васильковый Крайола","HexValue":"#9ACEEB"},{"Name":"Небесный","HexValue":"#87CEEB"},{"Name":"Голубой Крайола","HexValue":"#80DAEB"},{"Name":"Бирюзово-голубой Крайола","HexValue":"#77DDE7"},{"Name":"Аквамариновый Крайола","HexValue":"#78DBE2"},{"Name":"Светло-голубой","HexValue":"#87CEFA"},{"Name":"Электрик","HexValue":"#7DF9FF"},{"Name":"Аквамариновый","HexValue":"#7FFFD4"},{"Name":"Бледно-синий","HexValue":"#AFEEEE"},{"Name":"Снежно-синий","HexValue":"#ACE5EE"},{"Name":"Панг","HexValue":"#C7FCEC"},{"Name":"Зелёный чай","HexValue":"#D0F0C0"},{"Name":"Очень бледный зелёный","HexValue":"#D8DEBA"},{"Name":"Жемчужно-белый","HexValue":"#EAE6CA"},{"Name":"Миндаль Крайола","HexValue":"#EFDECD"},{"Name":"Бледно-розовый","HexValue":"#FADADD"},{"Name":"Розовый поросёнок","HexValue":"#FDDDE6"},{"Name":"Тускло-розовый","HexValue":"#FFE4E1"},{"Name":"Пастельно-розовый","HexValue":"#FFD1DC"},{"Name":"Бледно розоватый","HexValue":"#FFCBDB"},{"Name":"Сладкая вата","HexValue":"#FFBCD9"},{"Name":"Лавандовый Крайола","HexValue":"#FCB4D5"},{"Name":"Розовая гвоздика","HexValue":"#FFAACC"},{"Name":"Светло-розовый","HexValue":"#FFB6C1"},{"Name":"Розовый","HexValue":"#FFC0CB"},{"Name":"Очень бледно-пурпурный","HexValue":"#E6BBC1"},{"Name":"Тусклый амарантово-розовый","HexValue":"#DDBEC3"},{"Name":"Чертополоховый (Чертополох)","HexValue":"#D8BFD8"},{"Name":"Чертополох Крайола","HexValue":"#EBC7DF"},{"Name":"Очень светлый фиолетовый","HexValue":"#EEBEF1"},{"Name":"Ярко-сиреневый","HexValue":"#E0B0FF"},{"Name":"Фиалковый","HexValue":"#EA8DF7"},{"Name":"Розово-фиолетовый","HexValue":"#EE82EE"},{"Name":"Светло-розовая фуксия","HexValue":"#F984EF"},{"Name":"Шокирующий розовый Крайола","HexValue":"#FB7EFD"},{"Name":"Розовая фуксия","HexValue":"#FF77FF"},{"Name":"Розовый фламинго","HexValue":"#FC74FD"},{"Name":"Гелиотроповый (Гелиотроп)","HexValue":"#DF73FF"},{"Name":"Орхидеевый (Орхидея)","HexValue":"#DA70D6"},{"Name":"Блестящий пурпурный","HexValue":"#DD80CC"},{"Name":"Светлая слива","HexValue":"#DDA0DD"},{"Name":"Орхидея Крайола","HexValue":"#E6A8D7"},{"Name":"Лавандовый розовый","HexValue":"#FBA0E3"},{"Name":"Блестящий пурпурно-розовый","HexValue":"#FF97BB"},{"Name":"Амарантово-розовый","HexValue":"#F19CBB"},{"Name":"Розовато-лиловый Крайола","HexValue":"#EF98AA"},{"Name":"Розовый щербет","HexValue":"#F78FA7"},{"Name":"Розовый (Пощекочи меня)","HexValue":"#FC89AC"},{"Name":"Лососевый Крайола","HexValue":"#FF9BAA"},{"Name":"Светлый пурпурно-розовый","HexValue":"#FFA8AF"},{"Name":"Ярко-мандариновый","HexValue":"#FFA089"},{"Name":"Цвет маленького мандарина","HexValue":"#FFA474"},{"Name":"Цвет загара Крайола","HexValue":"#FAA76C"},{"Name":"Светлый оранжевый","HexValue":"#FFA161"},{"Name":"Оранжево-розовый","HexValue":"#FF9966"},{"Name":"Лососевый","HexValue":"#FF8C69"},{"Name":"Яркий желтовато-розовый","HexValue":"#FF845C"},{"Name":"Насыщенный желтовато-розовый","HexValue":"#FF7A5C"},{"Name":"Коралловый","HexValue":"#FF7F50"},{"Name":"Огненный оранжевый","HexValue":"#FF7F49"},{"Name":"Манго-танго","HexValue":"#FF8243"},{"Name":"Оранжевый Крайола","HexValue":"#FF7538"},{"Name":"Скандальный оранжевый","HexValue":"#FF6E4A"},{"Name":"Томатный","HexValue":"#FF6347"},{"Name":"Оранжевая заря","HexValue":"#FD5E53"},{"Name":"Красно-оранжевый Крайола","HexValue":"#FF5349"},{"Name":"Глубокий желтовато-розовый","HexValue":"#F64A46"},{"Name":"Карминно-розовый","HexValue":"#EB4C42"},{"Name":"Лососево-оранжевый","HexValue":"#E55137"},{"Name":"Лососево-красный","HexValue":"#D95030"},{"Name":"Умеренный красновато-оранжевый","HexValue":"#D35339"},{"Name":"Тёмно-коралловый","HexValue":"#CD5B45"},{"Name":"Красное дерево Крайола","HexValue":"#CD4A4C"},{"Name":"Кирпично-красный","HexValue":"#CB4154"},{"Name":"Коричнево-малиновый Крайола","HexValue":"#C8385A"},{"Name":"Джазовый джем","HexValue":"#CA3767"},{"Name":"Телемагента","HexValue":"#CF3476"},{"Name":"Амарантовый светло-вишнёвый","HexValue":"#CD2682"},{"Name":"Королевская фуксия","HexValue":"#CA2C92"},{"Name":"Византийский","HexValue":"#BD33A4"},{"Name":"Красно-фиолетовый Крайола","HexValue":"#C0448F"},{"Name":"Шелковица Крайола","HexValue":"#C54B8C"},{"Name":"Фанданго","HexValue":"#B55489"},{"Name":"Тёмный пурпурно-розовый","HexValue":"#C76574"},{"Name":"Фузи-Вузи","HexValue":"#CC6666"},{"Name":"Тёмный розовый","HexValue":"#C76864"},{"Name":"Тёмный желтовато-розовый","HexValue":"#CC6C5C"},{"Name":"Индийский красный, каштановый","HexValue":"#CD5C5C"},{"Name":"Терракота","HexValue":"#CC4E5C"},{"Name":"Каштановый Крайола","HexValue":"#BC5D58"},{"Name":"Коричневый Крайола","HexValue":"#B4674D"},{"Name":"Светлый красновато-коричневый","HexValue":"#AA6651"},{"Name":"Сепия Крайола","HexValue":"#A5694F"},{"Name":"Светлый коричневый","HexValue":"#A86540"},{"Name":"Серовато-красновато-оранжевый","HexValue":"#B85D43"},{"Name":"Глубокий каштановый Крайола","HexValue":"#B94E48"},{"Name":"Перламутрово-розовый","HexValue":"#B44C43"},{"Name":"Розовая долина","HexValue":"#AB4E52"},{"Name":"Умеренный пурпурно-красный","HexValue":"#A73853"},{"Name":"Амарантово-пурпурный","HexValue":"#AB274F"},{"Name":"Насыщенный пурпурно-красный","HexValue":"#B32851"},{"Name":"Глубокий карминный","HexValue":"#A9203E"},{"Name":"Умеренный красный","HexValue":"#AB343A"},{"Name":"Бледно-карминный","HexValue":"#B03F35"},{"Name":"Средний карминный","HexValue":"#AF4035"},{"Name":"Коричневато-оранжевый","HexValue":"#B15124"},{"Name":"Сиена","HexValue":"#A0522D"},{"Name":"Оранжево-коричневый","HexValue":"#A65E2E"},{"Name":"Камелопардовый","HexValue":"#A25F2A"},{"Name":"Охра коричневая","HexValue":"#955F20"},{"Name":"Песочный серо-коричневый","HexValue":"#967117"},{"Name":"Светло-оливковый","HexValue":"#846A20"},{"Name":"Зелёно-коричневый","HexValue":"#826C34"},{"Name":"Коричнево-бежевый","HexValue":"#8A6642"},{"Name":"Светлый серовато-оливковый","HexValue":"#8B734B"},{"Name":"Умеренный жёлто-зелёный","HexValue":"#8B8940"},{"Name":"Шамуа","HexValue":"#A08040"},{"Name":"Тёмный серовато-жёлтый","HexValue":"#A47C45"},{"Name":"Медный","HexValue":"#B87333"},{"Name":"Тёмно-жёлтый","HexValue":"#B07D2B"},{"Name":"Тёмный оранжево-жёлтый","HexValue":"#C37629"},{"Name":"Охра","HexValue":"#CC7722"},{"Name":"Шоколадный","HexValue":"#D2691E"},{"Name":"Рыжий","HexValue":"#D77D31"},{"Name":"Бронзовый","HexValue":"#CD7F32"},{"Name":"Перу","HexValue":"#CD853F"},{"Name":"Ванильный","HexValue":"#D5713F"},{"Name":"Умеренный оранжевый","HexValue":"#E8793E"},{"Name":"Сиена жжёная","HexValue":"#E97451"},{"Name":"Огненная Сиенна Крайола","HexValue":"#EA7E5D"},{"Name":"Сырая охра","HexValue":"#D68A59"},{"Name":"Светлый желтовато-коричневый","HexValue":"#BB8B54"},{"Name":"Бледный серо-коричневый","HexValue":"#BC987E"},{"Name":"Желтовато-серый","HexValue":"#CAA885"},{"Name":"Медный Крайола","HexValue":"#DD9475"},{"Name":"Темно-лососевый","HexValue":"#E9967A"},{"Name":"Умеренный желтовато-розовый","HexValue":"#EE9374"},{"Name":"Умеренный розовый","HexValue":"#EE9086"},{"Name":"Светло-розово-лиловый","HexValue":"#EA899A"},{"Name":"Умеренный пурпурно-розовый","HexValue":"#E28090"},{"Name":"Лиловый","HexValue":"#DB7093"},{"Name":"Бледный фиолетово-красный","HexValue":"#D87093"},{"Name":"Румянец","HexValue":"#DE5D83"},{"Name":"Тёмно-розовый","HexValue":"#E75480"},{"Name":"Глубокий пурпурно-розовый","HexValue":"#EB5284"},{"Name":"Французский розовый","HexValue":"#F64A8A"},{"Name":"Фиолетово-красный Крайола","HexValue":"#F75394"},{"Name":"Дикая клубника Крайола","HexValue":"#FF43A4"},{"Name":"Персидский розовый","HexValue":"#FE28A2"},{"Name":"Глубокий розовый","HexValue":"#FF1493"},{"Name":"Мовеин (анилиновый пурпур)","HexValue":"#EF0097"},{"Name":"Модная фуксия","HexValue":"#F400A1"},{"Name":"Ярко-розовый","HexValue":"#FC0FC0"},{"Name":"Пурпурная пицца","HexValue":"#FF00CC"},{"Name":"Ярко-фиолетовый","HexValue":"#CD00CD"},{"Name":"Тёмно-фиолетовый","HexValue":"#9400D3"},{"Name":"Фиолетовый","HexValue":"#8B00FF"},{"Name":"Фиолетово-сизый","HexValue":"#8000FF"},{"Name":"Персидский синий","HexValue":"#6600FF"},{"Name":"Сине-лиловый","HexValue":"#8A2BE2"},{"Name":"Тёмная орхидея","HexValue":"#9932CC"},{"Name":"Пурпурное сердце","HexValue":"#7442C8"},{"Name":"Аспидно-синий","HexValue":"#6A5ACD"},{"Name":"Сине-фиолетовый Крайола","HexValue":"#7366BD"},{"Name":"Индиго Крайола","HexValue":"#5D76CB"},{"Name":"Синяя сталь","HexValue":"#4682B4"},{"Name":"Блестящий синий","HexValue":"#4285B4"},{"Name":"Тёмно-голубой","HexValue":"#3B83BD"},{"Name":"Синий Клейна","HexValue":"#3A75C4"},{"Name":"Светлый джинсовый","HexValue":"#2B6CC4"},{"Name":"Небесно-синий","HexValue":"#2271B3"},{"Name":"Зелёно-синий Крайола","HexValue":"#1164B4"},{"Name":"Джинсовый синий","HexValue":"#1560BD"},{"Name":"Тёмно-синий Крайола","HexValue":"#1974D2"},{"Name":"Королевский синий","HexValue":"#4169E1"},{"Name":"Синий Крайола","HexValue":"#1F75FE"},{"Name":"Защитно-синий","HexValue":"#1E90FF"},{"Name":"Цвет морской волны (Аква)","HexValue":"#008CF0"},{"Name":"Лазурный, Азур","HexValue":"#007FFF"},{"Name":"Синий Градуса","HexValue":"#007DFF"},{"Name":"Голубой","HexValue":"#00BFFF"},{"Name":"Цвет яйца дрозда","HexValue":"#00CCCC"},{"Name":"Синий цвета яиц странствующего дрозда","HexValue":"#1FCECB"},{"Name":"Бирюзовый","HexValue":"#30D5C8"},{"Name":"Светло-бирюзовый","HexValue":"#40E0D0"},{"Name":"Умеренно-бирюзовый","HexValue":"#48D1CC"},{"Name":"Трилистник Крайола","HexValue":"#45CEA2"},{"Name":"Умеренный аквамариновый","HexValue":"#66CDAA"},{"Name":"Пастельно-бирюзовый","HexValue":"#7FB5B5"},{"Name":"Светло-серо-синий","HexValue":"#84C3BE"},{"Name":"Очень светлый зеленовато-синий","HexValue":"#A3C6C0"},{"Name":"Серо-синий Крайола","HexValue":"#B0B7C6"},{"Name":"Очень светлый пурпурно-синий","HexValue":"#BAACC7"},{"Name":"Сиреневый","HexValue":"#C8A2C8"},{"Name":"Глициниевый (Глициния)","HexValue":"#C9A0DC"},{"Name":"Глициния Крайола","HexValue":"#CDA4DE"},{"Name":"Светлый стальной синий","HexValue":"#B0C4DE"},{"Name":"Очень светлый синий","HexValue":"#A6BDD7"},{"Name":"Дикий синий Крайола","HexValue":"#A2ADD0"},{"Name":"Ниагара","HexValue":"#9DB1CC"},{"Name":"Голубой колокольчик Крайола","HexValue":"#A2A2D0"},{"Name":"Пурпурное горное величие","HexValue":"#9D81BA"},{"Name":"Фиолетовый (пурпурный) Крайола","HexValue":"#926EAE"},{"Name":"Аметистовый","HexValue":"#9966CC"},{"Name":"Средний пурпурный","HexValue":"#9370D8"},{"Name":"Умеренный аспидно-синий","HexValue":"#7B68EE"},{"Name":"Васильковый","HexValue":"#6495ED"},{"Name":"Сине-серый Крайола","HexValue":"#6699CC"},{"Name":"Сизый","HexValue":"#79A0C1"},{"Name":"Светло-сине-серый","HexValue":"#6C92AF"},{"Name":"Светлый зеленовато-синий","HexValue":"#649A9E"},{"Name":"Серо-синий","HexValue":"#5F9EA0"},{"Name":"Пастельно-синий","HexValue":"#5D9B9B"},{"Name":"Светлый синевато-зелёный","HexValue":"#669E85"},{"Name":"Лиственный зелёный Крайола","HexValue":"#6DAE81"},{"Name":"Папоротник Крайола","HexValue":"#71BC78"},{"Name":"Бледно-зелёный","HexValue":"#89AC76"},{"Name":"Спаржа Крайола","HexValue":"#87A96B"},{"Name":"Спаржа","HexValue":"#7BA05B"},{"Name":"Умеренный желтовато-зелёный","HexValue":"#657F4B"},{"Name":"Резедово-зелёный","HexValue":"#587246"},{"Name":"Зелёный папоротник","HexValue":"#4F7942"},{"Name":"Насыщенный жёлтовато-зелёный","HexValue":"#478430"},{"Name":"Кленовый зелёный","HexValue":"#507D2A"},{"Name":"Тёмно-оливковый","HexValue":"#556832"},{"Name":"Серое хаки","HexValue":"#6A5F31"},{"Name":"Перламутрово-золотой","HexValue":"#705335"},{"Name":"Бежево-коричневый","HexValue":"#79553D"},{"Name":"Серовато-желтовато-коричневый","HexValue":"#785840"},{"Name":"Бледно-коричневый","HexValue":"#755C48"},{"Name":"Перламутрово-бежевый","HexValue":"#6A5D4D"},{"Name":"Бежево-серый","HexValue":"#6D6552"},{"Name":"Тростниково-зелёный","HexValue":"#6C7156"},{"Name":"Серый мох","HexValue":"#6C7059"},{"Name":"Серый бетон","HexValue":"#686C5E"},{"Name":"Кварцевый серый","HexValue":"#6C6960"},{"Name":"Мышино-серый","HexValue":"#646B63"},{"Name":"Тусклый серый","HexValue":"#696969"},{"Name":"Перламутрово-ежевичный","HexValue":"#6C6874"},{"Name":"Платиново-серый","HexValue":"#7F7679"},{"Name":"Голубино-синий","HexValue":"#606E8C"},{"Name":"Блестящий пурпурно-синий","HexValue":"#62639B"},{"Name":"Отдалённо-синий","HexValue":"#49678D"},{"Name":"Бриллиантово-синий","HexValue":"#3E5F8A"},{"Name":"Умеренный синий","HexValue":"#395778"},{"Name":"Фиолетово-синий","HexValue":"#354D73"},{"Name":"Умеренный зеленовато-синий","HexValue":"#30626B"},{"Name":"Перламутровый горечавково-синий","HexValue":"#2A6478"},{"Name":"Водная синь","HexValue":"#256D7B"},{"Name":"Мурена","HexValue":"#1C6B72"},{"Name":"Мокрый тропический лес","HexValue":"#17806D"},{"Name":"Зелёная сосна Крайола","HexValue":"#158078"},{"Name":"Сине-зелёный цвета окраски чирка (птица)","HexValue":"#008080"},{"Name":"Тёмный циан","HexValue":"#008B8B"},{"Name":"Блестящий синевато-зелёный","HexValue":"#009B76"},{"Name":"Нефритовый","HexValue":"#00A86B"},{"Name":"Зелёный трилистник","HexValue":"#009A63"},{"Name":"Пигментный зелёный","HexValue":"#00A550"},{"Name":"Тёмный пастельно-зелёный","HexValue":"#03C03C"},{"Name":"Малахитовый","HexValue":"#0BDA51"},{"Name":"Лаймово-зелёный","HexValue":"#32CD32"},{"Name":"Вердепомовый","HexValue":"#34C924"},{"Name":"Ирландский зелёный","HexValue":"#4CBB17"},{"Name":"Травяной","HexValue":"#5DA130"},{"Name":"Тёмный жёлто-зелёный","HexValue":"#57A639"},{"Name":"Майский зелёный","HexValue":"#4C9141"},{"Name":"Арлекин","HexValue":"#44944A"},{"Name":"Транспортный зелёный","HexValue":"#308446"},{"Name":"Сигнальный зелёный","HexValue":"#317F43"},{"Name":"Изумрудно-зелёный","HexValue":"#287233"},{"Name":"Травяной зелёный","HexValue":"#35682D"},{"Name":"Папоротниково-зелёный","HexValue":"#3D642D"},{"Name":"Охотничий зелёный","HexValue":"#355E3B"},{"Name":"Умеренный зелёный","HexValue":"#386646"},{"Name":"Патиново-зелёный","HexValue":"#316650"},{"Name":"Умеренный синевато-зелёный","HexValue":"#2F6556"},{"Name":"Аспидно-серый","HexValue":"#2F4F4F"},{"Name":"Сосновый зелёный","HexValue":"#2C5545"},{"Name":"Бирюзово-зелёный","HexValue":"#1E5945"},{"Name":"Мятно-зелёный","HexValue":"#20603D"},{"Name":"Перламутрово-зелёный","HexValue":"#1C542D"},{"Name":"Лиственно-зелёный","HexValue":"#2D572C"},{"Name":"Тёмный желтовато-зелёный","HexValue":"#304B26"},{"Name":"Бутылочно-зелёный","HexValue":"#343B29"},{"Name":"Пихтовый зелёный","HexValue":"#31372B"},{"Name":"Тёмный зеленовато-желтовато-зелёный","HexValue":"#313830"},{"Name":"Темный серовато-синий","HexValue":"#2C3337"},{"Name":"Антрацитово-серый","HexValue":"#293133"},{"Name":"Гранитовый серый (гранитный)","HexValue":"#2F353B"},{"Name":"Чёрно-зелёный","HexValue":"#343E40"},{"Name":"Зелёный мох","HexValue":"#2F4538"},{"Name":"Чёрно-оливковый","HexValue":"#3B3C36"},{"Name":"Серо-оливковый","HexValue":"#3E3B32"},{"Name":"Серо-коричневый","HexValue":"#403A3A"},{"Name":"Тёмный зеленовато-серый","HexValue":"#45433B"},{"Name":"Тёмно-серый","HexValue":"#49423D"},{"Name":"Тёмный синевато-чёрный","HexValue":"#464544"},{"Name":"Космос","HexValue":"#414A4C"},{"Name":"Железно-серый","HexValue":"#434B4D"},{"Name":"Сине-серый","HexValue":"#474B4E"},{"Name":"Графитовый серый","HexValue":"#474A51"},{"Name":"Сланцево-серый","HexValue":"#434750"},{"Name":"Антрацитовый","HexValue":"#464451"},{"Name":"Серовато-пурпурно-синий","HexValue":"#413D51"},{"Name":"Серовато-фиолетовый","HexValue":"#46394B"},{"Name":"Тёмно-пурпурный","HexValue":"#472A3F"},{"Name":"Тёмный красновато-пурпурный","HexValue":"#4F273A"},{"Name":"Тёмный черовато-пурпурный","HexValue":"#452D35"},{"Name":"Шоколадно-коричневый","HexValue":"#45322E"},{"Name":"Тёмный серовато-красный","HexValue":"#482A2A"},{"Name":"Кофейный","HexValue":"#442D25"},{"Name":"Махагон коричневый","HexValue":"#4C2F27"},{"Name":"Терракотовый","HexValue":"#4E3B31"},{"Name":"Коричневато-серый","HexValue":"#503D33"},{"Name":"Тёмный красновато-серый","HexValue":"#523C36"},{"Name":"Оливково-серый","HexValue":"#4D4234"},{"Name":"Тёмно-серо-коричневый","HexValue":"#483C32"},{"Name":"Жёлто-оливковый","HexValue":"#47402E"},{"Name":"Сероватый оливково-зелёный","HexValue":"#48442D"},{"Name":"Коричнево-серый","HexValue":"#464531"},{"Name":"Оливково-зелёный","HexValue":"#424632"},{"Name":"Винтовочный зелёный","HexValue":"#414833"},{"Name":"Серовато-оливковый","HexValue":"#52442C"},{"Name":"Серовато-коричневый","HexValue":"#5A3D30"},{"Name":"Серовато-красновато-коричневый","HexValue":"#5E3830"},{"Name":"Каштаново-коричневый","HexValue":"#633A34"},{"Name":"Сигнальный коричневый","HexValue":"#6C3B2A"},{"Name":"Умеренный коричневый","HexValue":"#673923"},{"Name":"Тёмно-коричневый","HexValue":"#654321"},{"Name":"Глиняный коричневый","HexValue":"#734222"},{"Name":"Перламутровый медный","HexValue":"#763C28"},{"Name":"Золотисто-каштановый","HexValue":"#712F26"},{"Name":"Оксид красный","HexValue":"#642424"},{"Name":"Винно-красный","HexValue":"#5E2129"},{"Name":"Тёмный пурпурно-красный","HexValue":"#5B1E31"},{"Name":"Бордово-фиолетовый","HexValue":"#641C34"},{"Name":"Тёмный красный","HexValue":"#681C23"},{"Name":"Перламутрово-рубиновый","HexValue":"#721422"},{"Name":"Пурпурно-красный","HexValue":"#75151E"},{"Name":"Коричнево-красный","HexValue":"#781F19"},{"Name":"Фалунский красный","HexValue":"#801818"},{"Name":"Насыщенный красновато-коричневый","HexValue":"#7F180D"},{"Name":"Коричнево-малиновый","HexValue":"#800000"},{"Name":"Тёмнокрасный","HexValue":"#8B0000"},{"Name":"Сангиновый (Сангина)","HexValue":"#92000A"},{"Name":"Кармин","HexValue":"#960018"},{"Name":"Бургундский","HexValue":"#900020"},{"Name":"Рубиново-красный","HexValue":"#9B111E"},{"Name":"Сигнальный красный","HexValue":"#A52019"},{"Name":"Карминно-красный","HexValue":"#A2231D"},{"Name":"Томатно-красный","HexValue":"#A12312"},{"Name":"Бисмарк-фуриозо","HexValue":"#A5260A"},{"Name":"Глубокий красновато-оранжевый","HexValue":"#A91D11"},{"Name":"Огненно-красный","HexValue":"#AF2B1E"},{"Name":"Кораллово-красный","HexValue":"#B32821"},{"Name":"Ориент красный","HexValue":"#B32428"},{"Name":"Коричнево-бордовый","HexValue":"#A52A2A"},{"Name":"Тёмный красновато-оранжевый","HexValue":"#9B2F1F"},{"Name":"Умбра жжёная","HexValue":"#8A3324"},{"Name":"Медно-коричневый","HexValue":"#8E402A"},{"Name":"Кирпичный","HexValue":"#884535"},{"Name":"Серовато-красный","HexValue":"#8C4743"},{"Name":"Кордованский","HexValue":"#893F45"},{"Name":"Серовато-пурпурно-красный","HexValue":"#8C4852"},{"Name":"Серовато-красновато-пурпурный","HexValue":"#7D4D5D"},{"Name":"Серовато-пурпурный","HexValue":"#72525C"},{"Name":"Баклажановый Крайола","HexValue":"#6E5160"},{"Name":"Красновато-коричневый (блошиный)","HexValue":"#755A57"},{"Name":"Умеренный серо-коричневый","HexValue":"#674C47"},{"Name":"Розово-эбонитовый","HexValue":"#674846"},{"Name":"Баклажанный Крайола","HexValue":"#614051"},{"Name":"Тёмная Византия","HexValue":"#5D3954"},{"Name":"Умеренный фиолетовый","HexValue":"#543964"},{"Name":"Умеренный пурпурно-синий","HexValue":"#423C63"},{"Name":"Серовато-синий","HexValue":"#4A545C"},{"Name":"Базальтово-серый","HexValue":"#4E5754"},{"Name":"Цвет мокрого асфальта с зелёным","HexValue":"#4E5452"},{"Name":"Цвет мокрого асфальта","HexValue":"#505050"},{"Name":"Ливерный","HexValue":"#534B4F"},{"Name":"Брезентово-серый","HexValue":"#4C514A"},{"Name":"Зелёно-серый","HexValue":"#4D5645"},{"Name":"Серая спаржа","HexValue":"#465945"},{"Name":"Фелдграу","HexValue":"#4D5D53"},{"Name":"Серовато-зелёный","HexValue":"#575E4E"},{"Name":"Маренго","HexValue":"#4C5866"},{"Name":"Насыщенный фиолетовый","HexValue":"#53377A"},{"Name":"Тёмный аспидно-синий","HexValue":"#483D8B"},{"Name":"Насыщенный пурпурно-синий","HexValue":"#474389"},{"Name":"Глубокий фиолетовый","HexValue":"#423189"},{"Name":"Персидский индиго","HexValue":"#32127A"},{"Name":"Полуночный чёрный","HexValue":"#191970"},{"Name":"Очень пурпурно-синий","HexValue":"#20155E"},{"Name":"Сигнальный синий","HexValue":"#1E2460"},{"Name":"Ультрамариново-синий","HexValue":"#20214F"},{"Name":"Ночной синий","HexValue":"#252850"},{"Name":"Океанская синь","HexValue":"#1D334A"},{"Name":"Сине-зелёный","HexValue":"#1F3A3D"},{"Name":"Зелёно-синий","HexValue":"#1F3438"},{"Name":"Перламутровый опаловый","HexValue":"#193737"},{"Name":"Цвет Красного моря","HexValue":"#1F4037"},{"Name":"Зелёный тёмный","HexValue":"#203A27"},{"Name":"Миртовый","HexValue":"#21421E"},{"Name":"Хромовый зелёный","HexValue":"#2E3A23"},{"Name":"Коричнево-зелёный","HexValue":"#39352A"},{"Name":"Серая умбра","HexValue":"#332F2C"},{"Name":"Сигнальный чёрный","HexValue":"#282828"},{"Name":"Чёрно-серый","HexValue":"#23282B"},{"Name":"Тёмный серо-синий","HexValue":"#26252D"},{"Name":"Сапфирово-синий","HexValue":"#1D1E33"},{"Name":"Кобальтово-синий","HexValue":"#1E213D"},{"Name":"Глубокий пурпурно-синий","HexValue":"#1A153F"},{"Name":"Глубокий фиолетово-чёрный","HexValue":"#240935"},{"Name":"Очень глубокий пурпурный","HexValue":"#320B35"},{"Name":"Очень глубокий красновато-пурпурный","HexValue":"#470736"},{"Name":"Очень глубокий пурпурно-красный","HexValue":"#470027"},{"Name":"Очень глубокий красный","HexValue":"#4F0014"},{"Name":"Очень тёмный алый","HexValue":"#560319"},{"Name":"Розовый лес","HexValue":"#65000B"},{"Name":"Глубокий красный","HexValue":"#7B001C"},{"Name":"Глубокий пурпурно-красный","HexValue":"#6F0035"},{"Name":"Глубокий красновато-пурпурный","HexValue":"#641349"},{"Name":"Глубокий пурпурный","HexValue":"#531A50"},{"Name":"Пурпурно-фиолетовый","HexValue":"#4A192C"},{"Name":"Чёрно-красный","HexValue":"#412227"},{"Name":"Бистр","HexValue":"#3D2B1F"},{"Name":"Сепия коричневый","HexValue":"#382C1E"},{"Name":"Очень тёмный оливковый","HexValue":"#362C12"},{"Name":"Тёмный желтовато-коричневый","HexValue":"#3F2512"},{"Name":"Тёмный серовато-красновато-коричневый","HexValue":"#371F1C"},{"Name":"Тёмный серовато-коричневый","HexValue":"#32221A"},{"Name":"Тёмный серовато-оливковый","HexValue":"#2B2517"},{"Name":"Тёмно-сероватый оливково-зелёный","HexValue":"#27261A"},{"Name":"Коричнево-оливковый","HexValue":"#25221B"},{"Name":"Чёрно-коричневый","HexValue":"#212121"},{"Name":"Транспортный чёрный","HexValue":"#1E1E1E"},{"Name":"Графитно-чёрный","HexValue":"#1C1C1C"},{"Name":"Чёрно-синий","HexValue":"#18171C"},{"Name":"Черновато-синий","HexValue":"#161A1E"},{"Name":"Синевато-чёрный","HexValue":"#151719"},{"Name":"Черновато-зелёный","HexValue":"#141613"},{"Name":"Почти чёрный","HexValue":"#131313"},{"Name":"Зеленовато-чёрный","HexValue":"#181513"},{"Name":"Пурпурно-чёрный","HexValue":"#1B1116"},{"Name":"Черновато-пурпурный","HexValue":"#1D1018"},{"Name":"Красновато-чёрный","HexValue":"#1E1112"},{"Name":"Черновато-красный","HexValue":"#1F0E11"},{"Name":"Коричневато-чёрный","HexValue":"#140F0B"},{"Name":"Чёрный янтарь","HexValue":"#0A0A0A"},{"Name":"Чёрный","HexValue":"#000000"},{"Name":"Оливково-чёрный","HexValue":"#121910"},{"Name":"Очень тёмный желтовато-зелёный","HexValue":"#132712"},{"Name":"Очень тёмный зелёный","HexValue":"#16251C"},{"Name":"Тёмный оливково-зелёный","HexValue":"#232C16"},{"Name":"Тёмный оливково-коричневый","HexValue":"#302112"},{"Name":"Коричневый тёмный","HexValue":"#35170C"},{"Name":"Ивово-коричневый","HexValue":"#321414"},{"Name":"Тёмный красновато-коричневый","HexValue":"#321011"},{"Name":"Очень тёмный красный","HexValue":"#320A18"},{"Name":"Очень тёмный пурпурно-красный","HexValue":"#28071A"},{"Name":"Очень тёмный красновато-пурпурный","HexValue":"#270A1F"},{"Name":"Очень тёмно-пурпурный","HexValue":"#230D21"},{"Name":"Стально-синий","HexValue":"#231A24"},{"Name":"Тёмный пурпурно-синий","HexValue":"#1A162A"},{"Name":"Очень тёмный зеленовато-синий","HexValue":"#022027"},{"Name":"Очень тёмный синевато-зелёный","HexValue":"#001D18"},{"Name":"Тёмно-зелёный","HexValue":"#013220"},{"Name":"Глубокий синевато-зелёный","HexValue":"#00382B"},{"Name":"Темный синевато-зелёный","HexValue":"#013A33"},{"Name":"Тёмный зеленовато-синий","HexValue":"#003841"},{"Name":"Берлинская лазурь (Цвет Берлинской лазури)","HexValue":"#003153"},{"Name":"Глубокий синий","HexValue":"#002F55"},{"Name":"Перламутровый ночной","HexValue":"#102C54"},{"Name":"Горечавково-синий","HexValue":"#0E294B"},{"Name":"Тёмно-синий","HexValue":"#002137"},{"Name":"Фталоцианитовый зелёный","HexValue":"#123524"},{"Name":"Глубокий зелёный","HexValue":"#004524"},{"Name":"Глубокий желтовато-зелёный","HexValue":"#00541F"},{"Name":"Зелёный Мичиганского государственного университета","HexValue":"#006633"},{"Name":"Насыщенный зелёный","HexValue":"#006B3C"},{"Name":"Дартмутский зелёный","HexValue":"#00693E"},{"Name":"Яркий зелёный","HexValue":"#007D34"},{"Name":"Тёмный весенне-зелёный","HexValue":"#177245"},{"Name":"Насыщенный синевато-зелёный","HexValue":"#006D5B"},{"Name":"Опаловый зелёный","HexValue":"#015D52"},{"Name":"Зелёный орёл","HexValue":"#004953"},{"Name":"Мертвенный индиго","HexValue":"#00416A"},{"Name":"Транспортный синий","HexValue":"#063971"},{"Name":"Полуночно-синий","HexValue":"#003366"},{"Name":"Сапфировый","HexValue":"#082567"},{"Name":"Тёмно-лазурный","HexValue":"#08457E"},{"Name":"Цвет Чёрного моря","HexValue":"#1A4780"},{"Name":"Полуночный синий Крайола","HexValue":"#1A4876"},{"Name":"Капри синий","HexValue":"#1B5583"},{"Name":"Насыщенный синий","HexValue":"#00538A"},{"Name":"Насыщенный зеленовато-синий","HexValue":"#00677E"},{"Name":"Зелёная сосна","HexValue":"#01796F"},{"Name":"Яркий синевато-зелёный","HexValue":"#00836E"},{"Name":"Тёмно-бирюзовый","HexValue":"#116062"},{"Name":"Лазурно-синий","HexValue":"#025669"},{"Name":"Синяя пыль (Цвет синей пыли)","HexValue":"#003399"},{"Name":"Кобальт синий (Кобальтовый)","HexValue":"#0047AB"},{"Name":"Средний персидский синий","HexValue":"#0067A5"},{"Name":"Лазурно-серый (Зеленовато-синий)","HexValue":"#007BA7"},{"Name":"Ярко-синий","HexValue":"#007CAD"},{"Name":"Воды пляжа Бонди","HexValue":"#0095B6"},{"Name":"Сине-зелёный Крайола","HexValue":"#0D98BA"},{"Name":"Синий чирок","HexValue":"#18A7B5"},{"Name":"Светлое зелёное море","HexValue":"#20B2AA"},{"Name":"Горный луг","HexValue":"#30BA8F"},{"Name":"Зелёные джунгли Крайола","HexValue":"#3BB08F"},{"Name":"Зелёные джунгли Крайола 1990 года","HexValue":"#29AB87"},{"Name":"Зелёный Крайола","HexValue":"#1CAC78"},{"Name":"Море умеренного зелёного цвета","HexValue":"#3CB371"},{"Name":"Блестящий зелёный","HexValue":"#47A76A"},{"Name":"Изумрудный","HexValue":"#50C878"},{"Name":"Пастельно-зелёный","HexValue":"#77DD77"},{"Name":"Кричащий зелёный","HexValue":"#76FF7A"},{"Name":"Светло-зелёный","HexValue":"#90EE90"},{"Name":"Бледный зелёный","HexValue":"#98FB98"},{"Name":"Мята (Цвет зелёной мяты)","HexValue":"#98FF98"},{"Name":"Салатовый","HexValue":"#99FF99"},{"Name":"Фисташковый","HexValue":"#BEF574"},{"Name":"Жёлто-зелёный Крайола","HexValue":"#C5E384"},{"Name":"Обычный весенний бутон","HexValue":"#C9DC87"},{"Name":"Очень светлый желтовато-зелёный","HexValue":"#C6DF90"},{"Name":"Вердепешевый","HexValue":"#DAD871"},{"Name":"Светлый жёлто-зелёный","HexValue":"#DCD36A"},{"Name":"Жёлтая слоновая кость","HexValue":"#E1CC4F"},{"Name":"Пастельно-жёлтый","HexValue":"#EFA94A"},{"Name":"Неоново-морковный","HexValue":"#FFA343"},{"Name":"Жёлто-оранжевый Крайола","HexValue":"#FFAE42"},{"Name":"Блестящий оранжевый","HexValue":"#FFB841"},{"Name":"Бриллиантовыый оранжево-жёлтый","HexValue":"#FFB02E"},{"Name":"Люминесцентный ярко-оранжевый","HexValue":"#FFA420"},{"Name":"Тёмно-мандариновый","HexValue":"#FFA812"},{"Name":"Солнечно-жёлтый","HexValue":"#F39F18"},{"Name":"Насыщенный жёлтый","HexValue":"#E59E1F"},{"Name":"Золотисто-берёзовый","HexValue":"#DAA520"},{"Name":"Насыщенный зеленовато-жёлтый","HexValue":"#CCA817"},{"Name":"Тёмно-грушевый","HexValue":"#D8A903"},{"Name":"Жёлтый ракитник","HexValue":"#D6AE01"},{"Name":"Нарциссово-жёлтый","HexValue":"#DC9D00"},{"Name":"Гуммигут","HexValue":"#E49B0F"},{"Name":"Кукурузно-жёлтый","HexValue":"#E4A010"},{"Name":"Георгиново-жёлтый","HexValue":"#F3A505"},{"Name":"Дынно-жёлтый","HexValue":"#F4A900"},{"Name":"Оранжевый","HexValue":"#FFA500"},{"Name":"Кожура-апельсина","HexValue":"#FFA000"},{"Name":"Сигнальный оранжевый","HexValue":"#FF9900"},{"Name":"Яркий оранжево-жёлтый","HexValue":"#FF8E00"},{"Name":"Тёмно-оранжевый","HexValue":"#FF8C00"},{"Name":"Насыщенный оранжево-жёлтый","HexValue":"#FF8E0D"},{"Name":"Последний вздох Жако","HexValue":"#FF9218"},{"Name":"Светло-Морковный","HexValue":"#ED9121"},{"Name":"Насыщенный оранжевый","HexValue":"#EC7C26"},{"Name":"Тыква (Тыквенный)","HexValue":"#FF7518"},{"Name":"Пастельно-оранжевый","HexValue":"#FF7514"},{"Name":"Жёлто-оранжевый","HexValue":"#ED760E"},{"Name":"Мандариновый","HexValue":"#F28500"},{"Name":"Тёмный янтарь","HexValue":"#FF7E00"},{"Name":"Яркий оранжевый","HexValue":"#FF6800"},{"Name":"Международный оранжевый (Сигнальный)","HexValue":"#FF4F00"},{"Name":"Киноварь","HexValue":"#FF4D00"},{"Name":"Яркий красновато-оранжевый","HexValue":"#F13A13"},{"Name":"Транспортный оранжевый","HexValue":"#F54021"},{"Name":"Гранатовый","HexValue":"#F34723"},{"Name":"Ярко-красно-оранжевый","HexValue":"#F75E25"},{"Name":"Морковный","HexValue":"#F36223"},{"Name":"Светло-тициановый","HexValue":"#D84B20"},{"Name":"Красно-оранжевый","HexValue":"#C93C20"},{"Name":"Тёмно-алый","HexValue":"#CB2821"},{"Name":"Цвет пожарной машины","HexValue":"#CE2029"},{"Name":"Малиново-красный","HexValue":"#C51D34"},{"Name":"Кардинал","HexValue":"#C41E3A"},{"Name":"Насыщенный красный","HexValue":"#BF2233"},{"Name":"Персидский красный","HexValue":"#CC3333"},{"Name":"Клубнично-красный","HexValue":"#D53032"},{"Name":"Ализариновый красный","HexValue":"#E32636"},{"Name":"Глубокий карминно-розовый","HexValue":"#EF3038"},{"Name":"Светлый малиново-красный","HexValue":"#E63244"},{"Name":"Амарантовый","HexValue":"#E52B50"},{"Name":"Красный Крайола","HexValue":"#EE204D"},{"Name":"Скарлет","HexValue":"#FC2847"},{"Name":"Пламенная Маджента Крайола","HexValue":"#F8173E"},{"Name":"Американский розовый","HexValue":"#FF033E"},{"Name":"Карминово-красный","HexValue":"#FF0033"},{"Name":"Малиновый","HexValue":"#DC143C"},{"Name":"Яркий пурпурно-красный","HexValue":"#D5265B"},{"Name":"Светло-вишнёвый (Светлая вишня)","HexValue":"#DE3163"},{"Name":"Цвет суеты","HexValue":"#E3256B"},{"Name":"Грузинский розовый","HexValue":"#D71868"},{"Name":"Умеренный фиолетово-красный","HexValue":"#C71585"},{"Name":"Фиолетово-баклажанный","HexValue":"#991199"},{"Name":"Тёмный маджента","HexValue":"#8B008B"},{"Name":"Пурпурный","HexValue":"#800080"},{"Name":"Баклажановый","HexValue":"#990066"},{"Name":"Яркий красновато-пурпурный","HexValue":"#7E0059"},{"Name":"Сливовый","HexValue":"#660066"},{"Name":"Индиго","HexValue":"#4B0082"},{"Name":"Тёмный пурпурно-фиолетовый","HexValue":"#660099"},{"Name":"Византия","HexValue":"#702963"},{"Name":"Красно-сиреневый","HexValue":"#6D3F5B"},{"Name":"Сине-сиреневый","HexValue":"#6C4675"},{"Name":"Умеренный пурпурный","HexValue":"#7F4870"},{"Name":"Насыщенный","HexValue":"#803E75"},{"Name":"Умеренный красновато-пурпурный","HexValue":"#8C4566"},{"Name":"Насыщенный красновато-пурпурный","HexValue":"#9A366B"},{"Name":"Розовато-лиловый","HexValue":"#993366"},{"Name":"Амарантово-глубоко-пурпурный","HexValue":"#9F2B68"},{"Name":"Транспортный пурпурный","HexValue":"#A03472"},{"Name":"Малиново-розовый","HexValue":"#B3446C"},{"Name":"Розово-серо-коричневый","HexValue":"#905D5D"},{"Name":"Известковая глина","HexValue":"#79443B"},{"Name":"Умеренный желтовато-коричневый","HexValue":"#7D512D"},{"Name":"Оливково-коричневый","HexValue":"#6F4F28"},{"Name":"Сырая умбра","HexValue":"#714B23"},{"Name":"Натуральная умбра","HexValue":"#734A12"},{"Name":"Сепия (каракатица)","HexValue":"#704214"},{"Name":"Умеренный оливково-коричневый","HexValue":"#64400F"},{"Name":"Умеренно-оливковый","HexValue":"#5E490F"},{"Name":"Глубокий желтовато-коричневый","HexValue":"#593315"},{"Name":"Олень коричневый","HexValue":"#59351F"},{"Name":"Орехово-коричневый","HexValue":"#5B3A29"},{"Name":"Красно-коричневый","HexValue":"#592321"},{"Name":"Глубокий коричневый","HexValue":"#4D220E"},{"Name":"Блошиного брюшка","HexValue":"#4E1609"},{"Name":"Болгарский розовый","HexValue":"#480607"},{"Name":"Глубокий красновато-коричневый","HexValue":"#490005"},{"Name":"Бурый","HexValue":"#45161C"},{"Name":"Умеренный оливково-зелёный","HexValue":"#434B1B"},{"Name":"Глубокий жёлто-зелёный","HexValue":"#425E17"},{"Name":"Тёмный пурпурно-серый","HexValue":"#564042"},{"Name":"Красно-желтовато-коричневый","HexValue":"#80461B"},{"Name":"Цвет медвежьего ушка","HexValue":"#834d18"},{"Name":"Коричневый цвета кожанного седла для лошади","HexValue":"#8B4513"},{"Name":"Насыщенный желтовато-коричневый","HexValue":"#95500C"},{"Name":"Коричневый","HexValue":"#964B00"},{"Name":"Светлый оливково-коричневый","HexValue":"#945D0B"},{"Name":"Глубокий зеленовато-жёлтый","HexValue":"#9F8200"},{"Name":"Медово-жёлтый","HexValue":"#A98307"},{"Name":"Тёмный золотарник (Тёмно-золотой)","HexValue":"#B8860B"},{"Name":"Глубокий жёлтый","HexValue":"#B57900"},{"Name":"Карри жёлтый","HexValue":"#9D9101"},{"Name":"Яркий желтовато-зелёный","HexValue":"#93AA00"},{"Name":"Насыщенный жёлто-зелёный","HexValue":"#7F8F18"},{"Name":"Нежно-оливковый","HexValue":"#6B8E23"},{"Name":"Оливковый","HexValue":"#808000"},{"Name":"Тёмный зеленовато-жёлтый","HexValue":"#9B8127"},{"Name":"Перламутрово-оранжевый","HexValue":"#C35831"},{"Name":"Киноварь (китайский красный)","HexValue":"#E34234"},{"Name":"Глубокий коралловый","HexValue":"#FF4040"},{"Name":"Оранжево-красный Крайола","HexValue":"#FF2B2B"},{"Name":"Алый","HexValue":"#FF2400"},{"Name":"Красный","HexValue":"#FF0000"},{"Name":"Люминесцентный красный","HexValue":"#F80000"},{"Name":"Транспортный красный","HexValue":"#CC0605"},{"Name":"Бордовый","HexValue":"#B00000"},{"Name":"Яркий красный","HexValue":"#C10020"},{"Name":"Вишнёвый (Вишня)","HexValue":"#911E42"},{"Name":"Красно-фиолетовый","HexValue":"#922B3E"},{"Name":"Насыщенный коричневый","HexValue":"#753313"},{"Name":"Коричный","HexValue":"#7B3F00"},{"Name":"Ржаво-коричневый","HexValue":"#B7410E"},{"Name":"Красное дерево","HexValue":"#C04000"},{"Name":"Глубокий оранжевый","HexValue":"#C34D0A"},{"Name":"Выгоревший оранжевый (жжёный апельсин)","HexValue":"#CC5500"},{"Name":"Краснобуро-оранжевый","HexValue":"#CD5700"},{"Name":"Глубокий оранжево-жёлтый","HexValue":"#D76E00"},{"Name":"Тициановый","HexValue":"#D53E07"},{"Name":"Светло-карминово-розовый","HexValue":"#E66761"},{"Name":"Розовый антик","HexValue":"#D36E70"},{"Name":"Вересково-фиолетовый","HexValue":"#DE4C8A"},{"Name":"Светло-вишнёвый Крайола","HexValue":"#DD4492"},{"Name":"Крутой розовый Крайола","HexValue":"#FB607F"},{"Name":"Дикий арбуз Крайола","HexValue":"#FC6C85"},{"Name":"Насыщенный пурпурно-розовый","HexValue":"#F6768E"},{"Name":"Пылкий розовый","HexValue":"#FF7E93"},{"Name":"Насыщенный розовый","HexValue":"#FD7B7C"},{"Name":"Горько-сладкий","HexValue":"#FD7C6E"},{"Name":"Красный песок","HexValue":"#F4A460"},{"Name":"Насыщенный красновато-оранжевый","HexValue":"#FFB961"},{"Name":"Кукурузный","HexValue":"#FBEC5D"},{"Name":"Лимонно-жёлтый Крайола","HexValue":"#FFF44F"},{"Name":"Незрелый жёлтый","HexValue":"#FFFF66"},{"Name":"Цинково-жёлтый","HexValue":"#F8F32B"},{"Name":"Лазерный лимон","HexValue":"#FEFE22"},{"Name":"Цвет детской неожиданности","HexValue":"#F7F21A"},{"Name":"Лимонный","HexValue":"#FDE910"},{"Name":"Рапсово-жёлтый","HexValue":"#F3DA0B"},{"Name":"Транспортно-жёлтый","HexValue":"#FAD201"},{"Name":"Золотой (Золотистый)","HexValue":"#FFD700"},{"Name":"Цвет жёлтого школьного автобуса","HexValue":"#FFD800"},{"Name":"Цвет Яндекса","HexValue":"#FFCC00"},{"Name":"Яркий зеленовато-жёлтый","HexValue":"#F4C800"},{"Name":"Янтарный","HexValue":"#FFBF00"},{"Name":"Отборный жёлтый","HexValue":"#FFBA00"},{"Name":"Ярко-жёлтый","HexValue":"#FFB300"},{"Name":"Сигнальный жёлтый","HexValue":"#E5BE01"},{"Name":"Блестящий зеленовато-жёлтый","HexValue":"#FFDC33"},{"Name":"Жёлтая сера","HexValue":"#EDFF21"},{"Name":"Электрик Лайм Крайола","HexValue":"#CEFF1D"},{"Name":"Электрик Лайм (Лаймовый)","HexValue":"#CCFF00"},{"Name":"Зелёно-лаймовый","HexValue":"#BFFF00"},{"Name":"Весенний бутон","HexValue":"#A7FC00"},{"Name":"Шартрез, ядовито-зелёный","HexValue":"#7FFF00"},{"Name":"Зелёная лужайка","HexValue":"#7CFC00"},{"Name":"Ярко-зелёный","HexValue":"#66FF00"},{"Name":"Зелёно-жёлтый","HexValue":"#ADFF2F"},{"Name":"Гусеница","HexValue":"#B2EC5D"},{"Name":"Июньский бутон","HexValue":"#BDDA57"},{"Name":"Блестящий желтовато-зелёный","HexValue":"#8CCB5E"},{"Name":"Жёлто-зелёный","HexValue":"#9ACD32"},{"Name":"Тёмное зелёное море","HexValue":"#8FBC8F"},{"Name":"Очень светлый зелёный","HexValue":"#98C793"},{"Name":"Агатовый серый","HexValue":"#B5B8B1"},{"Name":"Серебристо-серый","HexValue":"#8A9597"},{"Name":"Серобуромалиновый","HexValue":"#735184"},{"Name":"Яркий пурпурный","HexValue":"#943391"},{"Name":"Глубокая фуксия Крайола","HexValue":"#C154C1"},{"Name":"Фуксия Крайола","HexValue":"#C364C5"},{"Name":"Умеренный цвет орхидеи","HexValue":"#BA55D3"},{"Name":"Амарантовый маджента","HexValue":"#ED3CCA"},{"Name":"Экстравагантный розовый Крайола","HexValue":"#FF33CC"},{"Name":"Звезды в шоке","HexValue":"#FF47CA"},{"Name":"Фуксии (Фуксия)","HexValue":"#F754E1"},{"Name":"Маджента Крайола","HexValue":"#F664AF"},{"Name":"Радикальный красный","HexValue":"#FF496C"},{"Name":"Умеренный оранжево-жёлтый","HexValue":"#F7943C"},{"Name":"Жёлтый","HexValue":"#FFFF00"},{"Name":"Лимонно-кремовый","HexValue":"#FFFACD"},{"Name":"Кремово-жёлтый","HexValue":"#FFFDD0"},{"Name":"Светло-жёлтый золотистый","HexValue":"#FAFAD2"},{"Name":"Морской зелёный","HexValue":"#54FF9F"},{"Name":"Карибский зелёный","HexValue":"#1CD3A2"},{"Name":"Умеренный весенний зелёный","HexValue":"#00FA9A"},{"Name":"Весенне-зелёный (Зелёная весна)","HexValue":"#00FF7F"},{"Name":"Персидский зелёный","HexValue":"#00A693"},{"Name":"Блестящий зеленовато-синий","HexValue":"#2A8D9C"},{"Name":"Бирюзово-синий","HexValue":"#3F888F"},{"Name":"Мятно-бирюзовый","HexValue":"#497E76"},{"Name":"Ядовито-зелёный","HexValue":"#40826D"},{"Name":"Зелёно-морской (Зелёное море)","HexValue":"#2E8B57"},{"Name":"Цвет влюблённой жабы","HexValue":"#3CAA3C"},{"Name":"Лесной зелёный","HexValue":"#228B22"},{"Name":"Индийский зелёный","HexValue":"#138808"},{"Name":"Зелёный","HexValue":"#008000"},{"Name":"Мусульманский зелёный","HexValue":"#009900"},{"Name":"Тёмно-зелёный, травяной","HexValue":"#006400"},{"Name":"Насыщенный оливково-зелёный","HexValue":"#0A4500"},{"Name":"Очень глубокий желтовато-зелёный","HexValue":"#002800"},{"Name":"Глубокий оливково-зелёный","HexValue":"#142300"},{"Name":"Тёмный индиго","HexValue":"#310062"},{"Name":"Ультрамариновый","HexValue":"#120A8F"},{"Name":"Тёмно-синий, ультрамариновый","HexValue":"#00008B"},{"Name":"Тёмно-синий (цвет формы морских офицеров)","HexValue":"#000080"},{"Name":"Фиолетово-синий Крайола","HexValue":"#324AB2"},{"Name":"Тихоокеанский синий","HexValue":"#1CA9C9"},{"Name":"Лазурный Крайола","HexValue":"#1DACD6"},{"Name":"Ярко-бирюзовый","HexValue":"#08E8DE"},{"Name":"Циан, Цвет морской волны","HexValue":"#00FFFF"},{"Name":"Лайм","HexValue":"#00FF00"},{"Name":"Синий","HexValue":"#0000FF"},{"Name":"Маджента, Фуксия","HexValue":"#FF00FF"}]